pydfql/__init__.py
pydfql/display_filters.py
pydfql/exceptions.py
pydfql/factories.py
pydfql/helpers.py
pydfql/models.py
pydfql/slicers.py
pydfql/evaluators/__init__.py
pydfql/evaluators/common.py
pydfql/parsers/__init__.py
pydfql/parsers/common.py
pydfql/parsers/display_filter.py
tests/__init__.py
tests/test_csv_display_filter_example.py
tests/test_dict_display_filter.py
tests/test_dict_display_filter_shell.py
tests/test_display_filter_parser.py
tests/test_json_display_filter_example.py
tests/test_nmap_display_filter_example.py
tests/test_object_display_filter.py
tests/test_slicers.py
tests/test_sql_display_filter.py
tests/test_sqlite_display_filter_example.py
tests/test_table.py
pydfql-1.3.0.dist-info/LICENSE
pydfql-1.3.0.dist-info/METADATA
pydfql-1.3.0.dist-info/WHEEL
pydfql-1.3.0.dist-info/top_level.txt
pydfql-1.3.0.dist-info/RECORD
